repository/Repository.py
repository/__init__.py
repository_PyOak-0.0.1.dist-info/LICENSE.md
repository_PyOak-0.0.1.dist-info/METADATA
repository_PyOak-0.0.1.dist-info/WHEEL
repository_PyOak-0.0.1.dist-info/top_level.txt
repository_PyOak-0.0.1.dist-info/RECORD
