Metadata-Version: 2.1
Name: repository-PyOak
Version: 0.0.1
Summary: A dictionary like repository component in python.
Home-page: https://github.com/pyoak/repository
Author: Wyatt Castaneda
Author-email: wyatt.castaneda@gmail.com
License: UNKNOWN
Project-URL: Bug Tracker, https://github.com/pyoak/repository/issues
Platform: UNKNOWN
Classifier: Programming Language :: Python :: 3
Classifier: License :: OSI Approved :: MIT License
Classifier: Operating System :: OS Independent
Requires-Python: >=3.6
License-File: LICENSE.md
